tskr/__init__.py
tskr/test.py
tskr/_debug_pool_for_develop/temp_aes.py
tskr/parts/AES_crypt.py
tskr-1.0.8.dist-info/METADATA
tskr-1.0.8.dist-info/WHEEL
tskr-1.0.8.dist-info/entry_points.txt
tskr-1.0.8.dist-info/top_level.txt
tskr-1.0.8.dist-info/RECORD
