Metadata-Version: 2.1
Name: tskr
Version: 1.0.8
Summary: task management tool
Home-page: https://github.co.jp/
Author: team_tskr
Author-email: tskr.tools@gmail.com
License: CC0 v1.0
Platform: UNKNOWN
Classifier: Programming Language :: Python :: 3
Classifier: Topic :: Software Development :: Libraries
Classifier: License :: CC0 1.0 Universal (CC0 1.0) Public Domain Dedication
Requires-Dist: pycryptodome
Requires-Dist: fileinit
Requires-Dist: relpath
Requires-Dist: sout
